direl_ts_tool_kit/__init__.py
direl_ts_tool_kit/plot/__init__.py
direl_ts_tool_kit/plot/plot_style.py
direl_ts_tool_kit/plot/plot_ts.py
direl_ts_tool_kit/utilities/__init__.py
direl_ts_tool_kit/utilities/data_prep.py
direl_ts_tool_kit-0.10.0.dist-info/licenses/LICENCE
direl_ts_tool_kit-0.10.0.dist-info/METADATA
direl_ts_tool_kit-0.10.0.dist-info/WHEEL
direl_ts_tool_kit-0.10.0.dist-info/top_level.txt
direl_ts_tool_kit-0.10.0.dist-info/RECORD
