Metadata-Version: 2.4
Name: direl-ts-tool-kit
Version: 0.10.0
Summary: A toolbox for time series analysis and visualization.
Home-page: https://gitlab.com/direl/direl_tool_kit
Author: Diego Restrepo-Leal
Author-email: diegorestrepoleal@gmail.com
Classifier: Programming Language :: Python :: 3
Classifier: Programming Language :: Python :: 3.9
Classifier: License :: OSI Approved :: MIT License
Classifier: Operating System :: OS Independent
Classifier: Intended Audience :: Science/Research
Classifier: Topic :: Scientific/Engineering :: Visualization
Requires-Python: >=3.8
License-File: LICENCE
Requires-Dist: pandas>=1.0.0
Requires-Dist: numpy>=1.18.0
Requires-Dist: matplotlib>=3.0.0
Requires-Dist: openpyxl
Requires-Dist: seaborn
Requires-Dist: scipy
Dynamic: author
Dynamic: author-email
Dynamic: classifier
Dynamic: description
Dynamic: description-content-type
Dynamic: home-page
Dynamic: license-file
Dynamic: requires-dist
Dynamic: requires-python
Dynamic: summary
